__init__.py
az_storage_tools.py
constants.py
az_storage_tools-0.0.4.dist-info/LICENSE
az_storage_tools-0.0.4.dist-info/METADATA
az_storage_tools-0.0.4.dist-info/WHEEL
az_storage_tools-0.0.4.dist-info/top_level.txt
az_storage_tools-0.0.4.dist-info/RECORD
