Metadata-Version: 2.1
Name: az_storage_tools
Version: 0.0.4
Summary: Azure Storage tools for various operations
Author-email: Hakan Karaoguz <hakan.karaoguz@silo.ai>
Project-URL: Homepage, https://github.com/pypa/sampleproject
Project-URL: Issues, https://github.com/pypa/sampleproject/issues
Classifier: Programming Language :: Python :: 3
Classifier: License :: OSI Approved :: MIT License
Classifier: Operating System :: OS Independent
Requires-Python: >=3.8
License-File: LICENSE
Requires-Dist: azure-storage-blob >=12.19.0
